svjflatanalysis
