Metadata-Version: 1.1
Name: svjflatanalysis
Version: 0.5
Summary: Description text
Home-page: https://github.com/tklijnsma/svjflatanalysis.git
Author: Thomas Klijnsma
Author-email: tklijnsm@gmail.com
License: BSD 3-Clause License
Download-URL: https://github.com/tklijnsma/svjflatanalysis/archive/v0_5.tar.gz
Platform: UNKNOWN
